justin_wechat/__init__.py
justin_wechat/access_token.py
justin_wechat/customer.py
justin_wechat/department.py
justin_wechat/main.py
justin_wechat/message.py
justin_wechat/user.py
justin_wechat-1.0.0.dist-info/METADATA
justin_wechat-1.0.0.dist-info/WHEEL
justin_wechat-1.0.0.dist-info/top_level.txt
justin_wechat-1.0.0.dist-info/RECORD
