Metadata-Version: 2.1
Name: justin-wechat
Version: 1.0.0
Summary: UNKNOWN
Home-page: UNKNOWN
Author: Justin Yoo
Author-email: xg.y@outlook.com
License: UNKNOWN
Platform: UNKNOWN
Requires-Dist: json
Requires-Dist: requests
